cas2json/__init__.py
cas2json/constants.py
cas2json/enums.py
cas2json/exceptions.py
cas2json/flags.py
cas2json/parser.py
cas2json/patterns.py
cas2json/types.py
cas2json/utils.py
cas2json/cams/__init__.py
cas2json/cams/helpers.py
cas2json/cams/parser.py
cas2json/cams/processor.py
cas2json/cams/types.py
cas2json/cdsl/__init__.py
cas2json/cdsl/parser.py
cas2json/cdsl/processor.py
cas2json/cdsl/utils.py
cas2json/nsdl/__init__.py
cas2json/nsdl/constants.py
cas2json/nsdl/parser.py
cas2json/nsdl/processor.py
cas2json-1.2.0.dist-info/METADATA
cas2json-1.2.0.dist-info/WHEEL
cas2json-1.2.0.dist-info/licenses/LICENSES/GPL-3.0-or-later.txt
cas2json-1.2.0.dist-info/RECORD
