Metadata-Version: 2.4
Name: cas2json
Version: 1.2.0
Summary: Serialize financial statements to python objects
Project-URL: Homepage, https://github.com/BeyondIRR/cas2json
Project-URL: Repository, https://github.com/BeyondIRR/cas2json
Project-URL: Issues, https://github.com/BeyondIRR/cas2json/issues
Author-email: Aman Jagotra <dragnemperor@gmail.com>
Maintainer-email: Aman Jagotra <dragnemperor@gmail.com>, Avishrant Sharma <avishrants@gmail.com>, Sagar Chand Agarwal <sagar.agarwal@beyondirr.tech>, Priyanshu Rajput <priyanshu011109@gmail.com>
License-Expression: GPL-3.0-or-later
License-File: LICENSES/GPL-3.0-or-later.txt
Classifier: License :: OSI Approved :: GNU General Public License v3 or later (GPLv3+)
Classifier: Operating System :: OS Independent
Classifier: Programming Language :: Python :: 3.12
Classifier: Programming Language :: Python :: 3.13
Requires-Python: >=3.12
Requires-Dist: pymupdf>=1.24.0
Requires-Dist: python-dateutil<3,>=2.8.2
